optimeed/consolidate/__init__.py
optimeed/consolidate/fit.py
optimeed/consolidate/parametric_analysis.py
optimeed/consolidate/sensitivity_analysis.py
optimeed/consolidate/sensitivity_analysis_evaluation.py
optimeed/consolidate/__pycache__/__init__.cpython-310.pyc
optimeed/consolidate/__pycache__/fit.cpython-310.pyc
optimeed/consolidate/__pycache__/parametric_analysis.cpython-310.pyc
optimeed/consolidate/__pycache__/sensitivity_analysis.cpython-310.pyc
optimeed/consolidate/__pycache__/sensitivity_analysis_evaluation.cpython-310.pyc
optimeed/core/__init__.py
optimeed/core/additional_tools.py
optimeed/core/collection.py
optimeed/core/color_palette.py
optimeed/core/commonImport.py
optimeed/core/graphs.py
optimeed/core/graphs3.py
optimeed/core/inkscape_manager.py
optimeed/core/linkDataGraph.py
optimeed/core/myjson.py
optimeed/core/options.py
optimeed/core/tikzTranslator.py
optimeed/core/tools.py
optimeed/core/__pycache__/__init__.cpython-310.pyc
optimeed/core/__pycache__/additional_tools.cpython-310.pyc
optimeed/core/__pycache__/collection.cpython-310.pyc
optimeed/core/__pycache__/color_palette.cpython-310.pyc
optimeed/core/__pycache__/commonImport.cpython-310.pyc
optimeed/core/__pycache__/graphs.cpython-310.pyc
optimeed/core/__pycache__/graphs3.cpython-310.pyc
optimeed/core/__pycache__/inkscape_manager.cpython-310.pyc
optimeed/core/__pycache__/linkDataGraph.cpython-310.pyc
optimeed/core/__pycache__/myjson.cpython-310.pyc
optimeed/core/__pycache__/options.cpython-310.pyc
optimeed/core/__pycache__/tikzTranslator.cpython-310.pyc
optimeed/core/__pycache__/tools.cpython-310.pyc
optimeed/core/ansi2html/LICENSE
optimeed/core/ansi2html/__init__.py
optimeed/core/ansi2html/converter.py
optimeed/core/ansi2html/style.py
optimeed/core/ansi2html/util.py
optimeed/core/ansi2html/__pycache__/__init__.cpython-310.pyc
optimeed/core/ansi2html/__pycache__/converter.cpython-310.pyc
optimeed/core/ansi2html/__pycache__/style.cpython-310.pyc
optimeed-2.1.1.dist-info/LICENSE
optimeed-2.1.1.dist-info/METADATA
optimeed-2.1.1.dist-info/WHEEL
optimeed-2.1.1.dist-info/top_level.txt
optimeed-2.1.1.dist-info/RECORD
