Metadata-Version: 2.1
Name: optimeed
Version: 2.1.1
Summary: Framework for generating and manipulating data.
Home-page: https://git.immc.ucl.ac.be/chdegreef/optimeed
Author: Christophe De Greef
Author-email: christophe.degreef@uclouvain.be
License: UNKNOWN
Platform: UNKNOWN
Classifier: Programming Language :: Python :: 3
Classifier: License :: OSI Approved :: GNU General Public License v3 (GPLv3)
Classifier: Operating System :: OS Independent
Classifier: Development Status :: 3 - Alpha
Classifier: Topic :: Scientific/Engineering
Requires-Python: >=3.6
License-File: LICENSE
Requires-Dist: numpy
Requires-Dist: PyOpenGL
Requires-Dist: PyQt5
Requires-Dist: pytypes
Requires-Dist: SALib
Provides-Extra: with_matplotlib
Requires-Dist: matplotlib ; extra == 'with_matplotlib'
Provides-Extra: with_pandas
Requires-Dist: pandas ; extra == 'with_pandas'
Provides-Extra: with_plotly
Requires-Dist: plotly ; extra == 'with_plotly'
